testing_package_3_16_2024/__init__.py
testing_package_3_16_2024/testing_module.py
testing_package_3_16_2024-0.1.5.dist-info/entry_points.txt
testing_package_3_16_2024-0.1.5.dist-info/METADATA
testing_package_3_16_2024-0.1.5.dist-info/WHEEL
testing_package_3_16_2024-0.1.5.dist-info/RECORD
