Metadata-Version: 2.1
Name: testing-package-3-16-2024
Version: 0.1.5
Summary: This is a testing project
Home-page: https://github.com/manuelgilm/testing_package
Keywords: test1,test2
Author: Manuel Gil
Author-email: manuelgilsitio@gmail.com
Maintainer: Manuel Gil
Maintainer-email: manuelgilsitio@gmail.com
Requires-Python: >=3.9,<4.0
Classifier: Programming Language :: Python :: 3
Classifier: Programming Language :: Python :: 3.9
Classifier: Programming Language :: Python :: 3.10
Classifier: Programming Language :: Python :: 3.11
Classifier: Topic :: Software Development :: Build Tools
Classifier: Topic :: Software Development :: Libraries :: Python Modules
Project-URL: Repository, https://github.com/manuelgilm/testing_package
